{
  "symbol": "^CNXIT",
  "interval": "1m",
  "created_at": "2026-02-14T16:08:51.100695",
  "last_update": "2026-02-27T15:15:20.952034",
  "total_rows": 5990,
  "date_range": {
    "start": "2026-02-05 09:15:00+05:30",
    "end": "2026-02-26 15:29:00+05:30"
  },
  "data_quality": {
    "status": "passed",
    "last_validated": "2026-02-27T15:15:20.952041",
    "issues_count": 3,
    "validation_details": {}
  },
  "download_history": [
    {
      "timestamp": "2026-02-14T16:08:51.100695",
      "rows_added": 2615,
      "total_rows": 2615,
      "success": true
    },
    {
      "timestamp": "2026-02-17T08:11:25.965841",
      "rows_added": 375,
      "total_rows": 2990,
      "success": true
    },
    {
      "timestamp": "2026-02-18T15:21:19.675438",
      "rows_added": 375,
      "total_rows": 3365,
      "success": true
    },
    {
      "timestamp": "2026-02-19T15:22:13.343997",
      "rows_added": 375,
      "total_rows": 3740,
      "success": true
    },
    {
      "timestamp": "2026-02-20T16:36:17.541964",
      "rows_added": 375,
      "total_rows": 4115,
      "success": true
    },
    {
      "timestamp": "2026-02-22T15:01:26.556315",
      "rows_added": 375,
      "total_rows": 4490,
      "success": true
    },
    {
      "timestamp": "2026-02-24T15:40:30.345558",
      "rows_added": 375,
      "total_rows": 4865,
      "success": true
    },
    {
      "timestamp": "2026-02-25T15:42:39.369459",
      "rows_added": 375,
      "total_rows": 5240,
      "success": true
    },
    {
      "timestamp": "2026-02-27T15:15:20.952044",
      "rows_added": 750,
      "total_rows": 5990,
      "success": true
    }
  ]
}