{
  "symbol": "CONCOR.NS",
  "interval": "1d",
  "created_at": "2026-02-14T15:38:30.460931",
  "last_update": "2026-03-01T14:57:54.219146",
  "total_rows": 5876,
  "date_range": {
    "start": "2002-07-01 00:00:00+05:30",
    "end": "2026-02-27 00:00:00+05:30"
  },
  "data_quality": {
    "status": "passed",
    "last_validated": "2026-03-01T14:57:54.219153",
    "issues_count": 11,
    "validation_details": {}
  },
  "download_history": [
    {
      "timestamp": "2026-02-14T15:38:30.460931",
      "rows_added": 5866,
      "total_rows": 5866,
      "success": true
    },
    {
      "timestamp": "2026-02-17T08:08:17.041070",
      "rows_added": 1,
      "total_rows": 5867,
      "success": true
    },
    {
      "timestamp": "2026-02-18T15:18:11.414243",
      "rows_added": 1,
      "total_rows": 5868,
      "success": true
    },
    {
      "timestamp": "2026-02-19T15:19:04.120336",
      "rows_added": 1,
      "total_rows": 5869,
      "success": true
    },
    {
      "timestamp": "2026-02-20T16:33:08.904397",
      "rows_added": 1,
      "total_rows": 5870,
      "success": true
    },
    {
      "timestamp": "2026-02-22T14:58:18.269735",
      "rows_added": 1,
      "total_rows": 5871,
      "success": true
    },
    {
      "timestamp": "2026-02-24T15:37:17.424434",
      "rows_added": 1,
      "total_rows": 5872,
      "success": true
    },
    {
      "timestamp": "2026-02-25T15:39:28.010517",
      "rows_added": 1,
      "total_rows": 5873,
      "success": true
    },
    {
      "timestamp": "2026-02-27T15:12:12.757133",
      "rows_added": 2,
      "total_rows": 5875,
      "success": true
    },
    {
      "timestamp": "2026-03-01T14:57:54.219157",
      "rows_added": 1,
      "total_rows": 5876,
      "success": true
    }
  ]
}