{
  "symbol": "SHRIRAMFIN.NS",
  "interval": "5m",
  "created_at": "2026-02-14T18:11:51.580257",
  "last_update": "2026-02-17T08:10:02.245363",
  "total_rows": 4424,
  "date_range": {
    "start": "2025-11-20 09:15:00+05:30",
    "end": "2026-02-16 15:25:00+05:30"
  },
  "data_quality": {
    "status": "passed",
    "last_validated": "2026-02-17T08:10:02.245369",
    "issues_count": 2,
    "validation_details": {}
  },
  "download_history": [
    {
      "timestamp": "2026-02-14T18:11:51.580257",
      "rows_added": 4349,
      "total_rows": 4349,
      "success": true
    },
    {
      "timestamp": "2026-02-17T08:10:02.245372",
      "rows_added": 75,
      "total_rows": 4424,
      "success": true
    }
  ]
}