{
  "symbol": "SIEMENS.NS",
  "interval": "1m",
  "created_at": "2026-02-14T15:19:15.411005",
  "last_update": "2026-03-12T15:28:16.439719",
  "total_rows": 8990,
  "date_range": {
    "start": "2026-02-05 09:15:00+05:30",
    "end": "2026-03-11 15:29:00+05:30"
  },
  "data_quality": {
    "status": "passed",
    "last_validated": "2026-03-12T15:28:16.439727",
    "issues_count": 2,
    "validation_details": {}
  },
  "download_history": [
    {
      "timestamp": "2026-02-14T15:19:15.411005",
      "rows_added": 2619,
      "total_rows": 2619,
      "success": true
    },
    {
      "timestamp": "2026-02-17T08:04:34.086534",
      "rows_added": 375,
      "total_rows": 2994,
      "success": true
    },
    {
      "timestamp": "2026-02-18T15:14:28.675453",
      "rows_added": 375,
      "total_rows": 3369,
      "success": true
    },
    {
      "timestamp": "2026-02-19T15:15:20.549228",
      "rows_added": 375,
      "total_rows": 3744,
      "success": true
    },
    {
      "timestamp": "2026-02-20T16:29:25.295764",
      "rows_added": 375,
      "total_rows": 4119,
      "success": true
    },
    {
      "timestamp": "2026-02-22T14:54:35.668540",
      "rows_added": 375,
      "total_rows": 4494,
      "success": true
    },
    {
      "timestamp": "2026-02-24T15:33:34.315165",
      "rows_added": 375,
      "total_rows": 4869,
      "success": true
    },
    {
      "timestamp": "2026-02-25T15:35:42.812825",
      "rows_added": 374,
      "total_rows": 5243,
      "success": true
    },
    {
      "timestamp": "2026-02-27T15:08:29.398359",
      "rows_added": 748,
      "total_rows": 5991,
      "success": true
    },
    {
      "timestamp": "2026-03-01T14:51:11.320768",
      "rows_added": 375,
      "total_rows": 6366,
      "success": true
    },
    {
      "timestamp": "2026-03-03T11:36:48.862936",
      "rows_added": 375,
      "total_rows": 6741,
      "success": true
    },
    {
      "timestamp": "2026-03-05T15:14:37.626730",
      "rows_added": 375,
      "total_rows": 7116,
      "success": true
    },
    {
      "timestamp": "2026-03-07T14:51:40.936333",
      "rows_added": 749,
      "total_rows": 7865,
      "success": true
    },
    {
      "timestamp": "2026-03-10T15:18:33.814147",
      "rows_added": 375,
      "total_rows": 8240,
      "success": true
    },
    {
      "timestamp": "2026-03-12T15:28:16.439730",
      "rows_added": 750,
      "total_rows": 8990,
      "success": true
    }
  ]
}